<?xml version="1.0" encoding="utf-8" ?>
<dwsync>
<file name="4da2074bc54d2_2.jpg" server="C:/wamp/www/adminKedaiOnline/" local="129471919500000000" remote="129471919500000000" />
<file name="4da2074bc54d2_3.jpg" server="C:/wamp/www/adminKedaiOnline/" local="129471919500000000" remote="129471919500000000" />
<file name="4da3303e40890_1.jpg" server="C:/wamp/www/adminKedaiOnline/" local="129470139500000000" remote="129470139500000000" />
<file name="4da3303e40890_2.jpg" server="C:/wamp/www/adminKedaiOnline/" local="129470139500000000" remote="129470139500000000" />
<file name="4da5e9c0df206_2.jpg" server="C:/wamp/www/adminKedaiOnline/" local="129471925130000000" remote="129471925130000000" />
<file name="4da5e9c0df206_1.jpg" server="C:/wamp/www/adminKedaiOnline/" local="129471925130000000" remote="129471925130000000" />
<file name="4da3303e40890_3.jpg" server="C:/wamp/www/adminKedaiOnline/" local="129470139500000000" remote="129470139500000000" />
<file name="4da5e9c0df206_3.png" server="C:/wamp/www/adminKedaiOnline/" local="129471925130000000" remote="129471925130000000" />
<file name="4da2074bc54d2_1.jpg" server="C:/wamp/www/adminKedaiOnline/" local="129471919500000000" remote="129471919500000000" />
</dwsync>